{
    "DNDConfig": null,
    "__parentReadjusting__": false,
    "_height_": {
        "type": "string",
        "value": "41dp"
    },
    "_left_": {
        "type": "string",
        "value": "21dp"
    },
    "_margin_": [
        0,
        0,
        0,
        0
    ],
    "_orientation_": 6,
    "_padding_": [
        0,
        0,
        0,
        0
    ],
    "_percent_": true,
    "_skin_": "s6ec4e1728a746b5991e322e6833ffa0",
    "_top_": {
        "type": "string",
        "value": "0"
    },
    "_width_": {
        "type": "string",
        "value": "41dp"
    },
    "allboxes": [],
    "autogrowmode": 0,
    "canUpdateUI": true,
    "centery": {
        "type": "string",
        "value": "50%"
    },
    "children": [
        "imgWorkpack"
    ],
    "clipbounds": true,
    "containerId": true,
    "containerweight": 100,
    "enablescrolling": true,
    "id": "flxWorkPack",
    "info": null,
    "iscustomlayout": false,
    "isvisible": true,
    "kuid": "g52c2b6eec73499694746c54cda2efa1",
    "layouttype": 2,
    "name": "kony.ui.FlexContainer",
    "parent": "flxWorkPackMain",
    "pf": "workpackRowTemplate",
    "retaincontentalignment": false,
    "retainflexpositionproperties": false,
    "retainflowhorizontalalignment": false,
    "snapgridsize": 10,
    "snaptogrid": true,
    "wType": "FlexContainer",
    "widgetalignment": 1,
    "zindex": 1
}